LICENSE
MANIFEST.in
README.rst
requirements.txt
setup.cfg
setup.py
linkstore/__init__.py
linkstore/cli.py
linkstore/clock.py
linkstore/factory.py
linkstore/link.py
linkstore/link_storage.py
linkstore/linkstore.py
linkstore.egg-info/PKG-INFO
linkstore.egg-info/SOURCES.txt
linkstore.egg-info/dependency_links.txt
linkstore.egg-info/entry_points.txt
linkstore.egg-info/not-zip-safe
linkstore.egg-info/requires.txt
linkstore.egg-info/top_level.txt
spec/__init__.py
spec/fixtures.py
spec/helpers.py
spec/acceptance-integration/__init__.py
spec/acceptance-integration/changing_tags_spec.py
spec/acceptance-integration/deleting_links_spec.py
spec/acceptance-integration/retrieving_links_spec.py
spec/acceptance-integration/saving_links_spec.py
spec/end_to_end/__init__.py
spec/end_to_end/cli_spec.py
spec/unit/__init__.py
spec/unit/link_spec.py
spec/unit/link_storage_spec.py