Metadata-Version: 1.1
Name: linkstore
Version: 0.0.9
Summary: A dead-simple bookmarking CLI application
Home-page: https://github.com/angelsanz/linkstore
Author: Ángel Sanz
Author-email: angelsanzgit@gmail.com
License: MIT
Keywords: link hyperlink store storage
Platform: UNKNOWN
Classifier: Development Status :: 2 - Pre-Alpha
Classifier: Environment :: Console
Classifier: Intended Audience :: End Users/Desktop
Classifier: Intended Audience :: Information Technology
Classifier: Operating System :: POSIX :: Linux
Classifier: Programming Language :: Python :: 2.7
Classifier: Topic :: Database
Classifier: License :: OSI Approved :: MIT License
